Metadata-Version: 1.0
Name: expelliarmusBANANA
Version: 0.1.1
Summary: A Python Spell to apply data handling and segmentation magic to a dataframe.
Home-page: https://github.com/nalishamen/expelliarmusBANANA
Author: Nalisha Men
Author-email: nalisha.m@student.ie.edu
License: MIT
Platform: UNKNOWN
